multiobject/__init__.py
multiobject/_version.py
multiobject/base.py
multiobject/pytorch.py
multiobject-0.0.3.dist-info/LICENSE
multiobject-0.0.3.dist-info/METADATA
multiobject-0.0.3.dist-info/WHEEL
multiobject-0.0.3.dist-info/top_level.txt
multiobject-0.0.3.dist-info/RECORD
