Metadata-Version: 2.1
Name: multiobject
Version: 0.0.3
Summary: Tools to generate and use multi-object datasets
Home-page: https://github.com/addtt/multi-object-datasets
Author: Andrea Dittadi
Author-email: andrea.dittadi@gmail.com
License: UNKNOWN
Platform: UNKNOWN
Classifier: Programming Language :: Python :: 3
Classifier: License :: OSI Approved :: MIT License
Classifier: Operating System :: OS Independent
Requires-Python: >=3.6
Requires-Dist: numpy (>=1.17)
Requires-Dist: torch (>=1.4)
Requires-Dist: tqdm
